{
    "idCarrera": "dwars-door-vlaanderen",
    "anio": 1989,
    "distancia": 204.0,
    "desnivel": 0,
    "tiempo": "0h 00' 00\"",
    "ciclistasInscritos": 0,
    "ciclistasFinalizados": 25,
    "clasificacionGeneral": [
        {
            "puesto": 2,
            "nombre": "de Rooij Theo",
            "pais": "Países Bajos",
            "equipo": "Panasonic - Isostar",
            "ventaja": "0"
        },
        {
            "puesto": 3,
            "nombre": "Museeuw Johan",
            "pais": "Bélgica",
            "equipo": "ADR - Agrigel - Bottecchia",
            "ventaja": "0"
        },
        {
            "puesto": 4,
            "nombre": "Capiot Johan",
            "pais": "Bélgica",
            "equipo": "TVM ",
            "ventaja": "0"
        },
        {
            "puesto": 5,
            "nombre": "Frison Herman",
            "pais": "Bélgica",
            "equipo": "Histor - Sigma - Fina",
            "ventaja": "0"
        },
        {
            "puesto": 6,
            "nombre": "Willems Ludwig",
            "pais": "Bélgica",
            "equipo": "Lotto",
            "ventaja": "0"
        },
        {
            "puesto": 7,
            "nombre": "Verhoeven Nico",
            "pais": "Países Bajos",
            "equipo": "Superconfex - Yoko - Opel",
            "ventaja": "0"
        },
        {
            "puesto": 8,
            "nombre": "Van Lancker Eric",
            "pais": "Bélgica",
            "equipo": "Panasonic - Isostar",
            "ventaja": "0"
        },
        {
            "puesto": 9,
            "nombre": "Haex Jos",
            "pais": "Bélgica",
            "equipo": "Hitachi",
            "ventaja": "0"
        },
        {
            "puesto": 10,
            "nombre": "Mann David",
            "pais": "Reino Unido",
            "equipo": "Raleigh - Banana ",
            "ventaja": "0"
        }
    ],
    "ganadorPuntos": {},
    "ganadorMontana": {},
    "ganadorJovenes": {},
    "ganadorEquipos": {},
    "etapas": []
}