{
    "idCarrera": "eschborn-frankfurt",
    "anio": 1995,
    "distancia": 252.0,
    "desnivel": 0,
    "tiempo": "6h 25' 05\"",
    "ciclistasInscritos": 0,
    "ciclistasFinalizados": 91,
    "clasificacionGeneral": [
        {
            "puesto": 1,
            "nombre": "Frattini Francesco",
            "pais": "Italia",
            "equipo": "Gewiss - Ballan",
            "ventaja": "0"
        },
        {
            "puesto": 2,
            "nombre": "Heppner Jens",
            "pais": "Alemania",
            "equipo": "Team Deutsche Telekom",
            "ventaja": "0"
        },
        {
            "puesto": 3,
            "nombre": "Podenzana Massimo",
            "pais": "Italia",
            "equipo": "Brescialat",
            "ventaja": "+ 3 s"
        },
        {
            "puesto": 4,
            "nombre": "Tafi Andrea",
            "pais": "Italia",
            "equipo": "Mapei-GB   ",
            "ventaja": "+ 31 s"
        },
        {
            "puesto": 5,
            "nombre": "Zaina Enrico",
            "pais": "Italia",
            "equipo": "Carrera Jeans - Tassoni",
            "ventaja": "+ 31 s"
        },
        {
            "puesto": 6,
            "nombre": "Cenghialta Bruno",
            "pais": "Italia",
            "equipo": "Gewiss - Ballan",
            "ventaja": "+ 31 s"
        },
        {
            "puesto": 7,
            "nombre": "Fondriest Maurizio",
            "pais": "Italia",
            "equipo": "Lampre-Panaria  ",
            "ventaja": "+ 54 s"
        },
        {
            "puesto": 8,
            "nombre": "Museeuw Johan",
            "pais": "Bélgica",
            "equipo": "Mapei-GB   ",
            "ventaja": "+ 54 s"
        },
        {
            "puesto": 9,
            "nombre": "Zanini Stefano",
            "pais": "Italia",
            "equipo": "Gewiss - Ballan",
            "ventaja": "+ 54 s"
        },
        {
            "puesto": 10,
            "nombre": "Zberg Beat",
            "pais": "Suiza",
            "equipo": "Carrera Jeans - Tassoni",
            "ventaja": "+ 54 s"
        }
    ],
    "ganadorPuntos": {},
    "ganadorMontana": {},
    "ganadorJovenes": {},
    "ganadorEquipos": {},
    "etapas": []
}