{
    "idCarrera": "volta-ao-algarve",
    "anio": 1993,
    "distancia": 265.2,
    "desnivel": 0,
    "tiempo": "0h 00' 00\"",
    "ciclistasInscritos": 14,
    "ciclistasFinalizados": 10,
    "clasificacionGeneral": [
        {
            "puesto": 2,
            "nombre": "Carvalho Fernando Alberto Oliveira",
            "pais": "Portugal",
            "equipo": "Feirense - Imporbor",
            "ventaja": "0"
        },
        {
            "puesto": 3,
            "nombre": "Quevedo Fernando",
            "pais": "España",
            "equipo": "Amaya - Seguros",
            "ventaja": "0"
        },
        {
            "puesto": 4,
            "nombre": "Marques Santos Luis",
            "pais": "Portugal",
            "equipo": "Recer - Boavista ",
            "ventaja": "0"
        },
        {
            "puesto": 5,
            "nombre": "Martin Juan Carlos",
            "pais": "España",
            "equipo": "Amaya - Seguros",
            "ventaja": "0"
        },
        {
            "puesto": 6,
            "nombre": "Andrade Joaquim Adrego Pereira",
            "pais": "Portugal",
            "equipo": "Feirense - Imporbor",
            "ventaja": "0"
        },
        {
            "puesto": 7,
            "nombre": "González Bernardo",
            "pais": "España",
            "equipo": "Kelme",
            "ventaja": "0"
        },
        {
            "puesto": 8,
            "nombre": "Martín Antonio",
            "pais": "España",
            "equipo": "",
            "ventaja": "0"
        },
        {
            "puesto": 9,
            "nombre": "Benitez Francisco",
            "pais": "España",
            "equipo": "Kelme",
            "ventaja": "0"
        },
        {
            "puesto": 10,
            "nombre": "Pinto Paulo",
            "pais": "Portugal",
            "equipo": "",
            "ventaja": "0"
        }
    ],
    "ganadorPuntos": {},
    "ganadorMontana": {},
    "ganadorJovenes": {},
    "ganadorEquipos": {},
    "etapas": [
        {
            "etapa": 1,
            "nombre": "Pinto Paulo",
            "pais": "Portugal",
            "distancia": 0.0,
            "desnivel": 0,
            "velocidadMedia": null
        },
        {
            "etapa": 2,
            "nombre": "Quevedo Fernando",
            "pais": "España",
            "distancia": 128.0,
            "desnivel": 0,
            "velocidadMedia": null
        },
        {
            "etapa": 3,
            "nombre": "Martinez Juan Tomas",
            "pais": "España",
            "distancia": 0.0,
            "desnivel": 0,
            "velocidadMedia": null
        },
        {
            "etapa": 4,
            "nombre": "Silva Paulo Manuel Correia",
            "pais": "Portugal",
            "distancia": 0.0,
            "desnivel": 0,
            "velocidadMedia": null
        },
        {
            "etapa": 5,
            "nombre": "Santiago Jose",
            "pais": "Portugal",
            "distancia": 100.0,
            "desnivel": 0,
            "velocidadMedia": null
        },
        {
            "etapa": 5,
            "nombre": "Pedersen Per",
            "pais": "Dinamarca",
            "distancia": 9.0,
            "desnivel": 0,
            "velocidadMedia": null
        },
        {
            "etapa": 6,
            "nombre": "Freitas Cássio",
            "pais": "Brasil",
            "distancia": 28.2,
            "desnivel": 0,
            "velocidadMedia": 41.54
        },
        {
            "etapa": 7,
            "nombre": "Pinto Paulo",
            "pais": "Portugal",
            "distancia": 0.0,
            "desnivel": 0,
            "velocidadMedia": 41.538
        }
    ]
}