{
    "idCarrera": "ronde-van-vlaanderen",
    "anio": 1942,
    "distancia": 226.0,
    "desnivel": 0,
    "tiempo": "6h 26' 00\"",
    "ciclistasInscritos": 22,
    "ciclistasFinalizados": 22,
    "clasificacionGeneral": [
        {
            "puesto": 1,
            "nombre": "Schotte Briek",
            "pais": "Bélgica",
            "equipo": "",
            "ventaja": "0"
        },
        {
            "puesto": 2,
            "nombre": "Claes Georges",
            "pais": "Bélgica",
            "equipo": "",
            "ventaja": "+ 5 s"
        },
        {
            "puesto": 3,
            "nombre": "Van Eenaeme Robert",
            "pais": "Bélgica",
            "equipo": "",
            "ventaja": "+ 5 s"
        },
        {
            "puesto": 4,
            "nombre": "Grysolle Sylvain",
            "pais": "Bélgica",
            "equipo": "",
            "ventaja": "+ 5 s"
        },
        {
            "puesto": 5,
            "nombre": "Lowie Jules",
            "pais": "Bélgica",
            "equipo": "",
            "ventaja": "+ 5 s"
        },
        {
            "puesto": 6,
            "nombre": "Declerck André",
            "pais": "Bélgica",
            "equipo": "",
            "ventaja": "+ 5 s"
        },
        {
            "puesto": 7,
            "nombre": "Bonduel Frans",
            "pais": "Bélgica",
            "equipo": "",
            "ventaja": "+ 25 s"
        },
        {
            "puesto": 8,
            "nombre": "Maelbrancke André",
            "pais": "Bélgica",
            "equipo": "",
            "ventaja": "+ 1 min 25 s"
        },
        {
            "puesto": 9,
            "nombre": "Hendrickx Albert",
            "pais": "Bélgica",
            "equipo": "",
            "ventaja": "+ 1 min 40 s"
        },
        {
            "puesto": 10,
            "nombre": "Hermie Michel",
            "pais": "Bélgica",
            "equipo": "",
            "ventaja": "+ 3 min 10 s"
        }
    ],
    "ganadorPuntos": {},
    "ganadorMontana": {},
    "ganadorJovenes": {},
    "ganadorEquipos": {},
    "etapas": []
}