{
    "idCarrera": "ronde-van-vlaanderen",
    "anio": 2011,
    "distancia": 258.0,
    "desnivel": 2043,
    "tiempo": "6h 01' 20\"",
    "ciclistasInscritos": 199,
    "ciclistasFinalizados": 199,
    "clasificacionGeneral": [
        {
            "puesto": 1,
            "nombre": "Nuyens Nick",
            "pais": "Bélgica",
            "equipo": "Saxo Bank - Sungard",
            "ventaja": "0"
        },
        {
            "puesto": 2,
            "nombre": "Chavanel Sylvain",
            "pais": "Francia",
            "equipo": "Quickstep Cycling Team",
            "ventaja": "0"
        },
        {
            "puesto": 3,
            "nombre": "Cancellara Fabian",
            "pais": "Suiza",
            "equipo": "Leopard Trek",
            "ventaja": "0"
        },
        {
            "puesto": 4,
            "nombre": "Boonen Tom",
            "pais": "Bélgica",
            "equipo": "Quickstep Cycling Team",
            "ventaja": "+ 2 s"
        },
        {
            "puesto": 5,
            "nombre": "Langeveld Sebastian",
            "pais": "Países Bajos",
            "equipo": "Rabobank Cycling Team",
            "ventaja": "+ 5 s"
        },
        {
            "puesto": 6,
            "nombre": "Hincapie George",
            "pais": "Estados Unidos",
            "equipo": "BMC Racing Team",
            "ventaja": "+ 5 s"
        },
        {
            "puesto": 7,
            "nombre": "Leukemans Björn",
            "pais": "Bélgica",
            "equipo": "Vacansoleil - DCM",
            "ventaja": "+ 5 s"
        },
        {
            "puesto": 8,
            "nombre": "Scheirlinckx Staf",
            "pais": "Bélgica",
            "equipo": "Veranda's Willems - Accent",
            "ventaja": "+ 5 s"
        },
        {
            "puesto": 9,
            "nombre": "Gilbert Philippe",
            "pais": "Bélgica",
            "equipo": "Omega Pharma-Lotto ",
            "ventaja": "+ 5 s"
        },
        {
            "puesto": 10,
            "nombre": "Thomas Geraint",
            "pais": "Reino Unido",
            "equipo": "Sky Procycling",
            "ventaja": "+ 5 s"
        }
    ],
    "ganadorPuntos": {},
    "ganadorMontana": {},
    "ganadorJovenes": {},
    "ganadorEquipos": {},
    "etapas": []
}