{
    "idCarrera": "kuurne-brussel-kuurne",
    "anio": 1990,
    "distancia": 198.0,
    "desnivel": 0,
    "tiempo": "5h 04' 00\"",
    "ciclistasInscritos": 50,
    "ciclistasFinalizados": 50,
    "clasificacionGeneral": [
        {
            "puesto": 1,
            "nombre": "Redant Hendrik",
            "pais": "Bélgica",
            "equipo": "Lotto - Super Club",
            "ventaja": "0"
        },
        {
            "puesto": 2,
            "nombre": "Nijdam Jelle",
            "pais": "Países Bajos",
            "equipo": "Buckler - Colnago - Decca",
            "ventaja": "+ 7 s"
        },
        {
            "puesto": 3,
            "nombre": "Phinney Davis",
            "pais": "Estados Unidos",
            "equipo": "7 Eleven - Hoonved",
            "ventaja": "+ 7 s"
        },
        {
            "puesto": 4,
            "nombre": "Schurer Eddy",
            "pais": "Países Bajos",
            "equipo": "TVM - Toko",
            "ventaja": "+ 7 s"
        },
        {
            "puesto": 5,
            "nombre": "Dauwe Johnny",
            "pais": "Bélgica",
            "equipo": "Weinmann - SMM - Ulster",
            "ventaja": "+ 7 s"
        },
        {
            "puesto": 6,
            "nombre": "Demol Dirk",
            "pais": "Bélgica",
            "equipo": "Lotto - Super Club",
            "ventaja": "+ 7 s"
        },
        {
            "puesto": 7,
            "nombre": "Devos Johan",
            "pais": "Bélgica",
            "equipo": "S.E.F.B. - Saxon - Gan",
            "ventaja": "+ 7 s"
        },
        {
            "puesto": 8,
            "nombre": "Deneut Patrick",
            "pais": "Bélgica",
            "equipo": "Lotto - Super Club",
            "ventaja": "+ 10 s"
        },
        {
            "puesto": 9,
            "nombre": "Segers Noël",
            "pais": "Bélgica",
            "equipo": "Buckler - Colnago - Decca",
            "ventaja": "+ 10 s"
        },
        {
            "puesto": 10,
            "nombre": "Hendrikx Patrick",
            "pais": "Bélgica",
            "equipo": "Isoglass - Garden Wood",
            "ventaja": "+ 10 s"
        }
    ],
    "ganadorPuntos": {},
    "ganadorMontana": {},
    "ganadorJovenes": {},
    "ganadorEquipos": {},
    "etapas": []
}