{
    "idCarrera": "la-fleche-wallonne",
    "anio": 1954,
    "distancia": 220.0,
    "desnivel": 0,
    "tiempo": "6h 35' 48\"",
    "ciclistasInscritos": 63,
    "ciclistasFinalizados": 64,
    "clasificacionGeneral": [
        {
            "puesto": 1,
            "nombre": "Derycke Germain",
            "pais": "Bélgica",
            "equipo": "",
            "ventaja": "0"
        },
        {
            "puesto": 2,
            "nombre": "Kübler Ferdinand",
            "pais": "Suiza",
            "equipo": "",
            "ventaja": "0"
        },
        {
            "puesto": 3,
            "nombre": "De Valck Jan",
            "pais": "Bélgica",
            "equipo": "",
            "ventaja": "0"
        },
        {
            "puesto": 4,
            "nombre": "Van Geneugden Martin",
            "pais": "Bélgica",
            "equipo": "",
            "ventaja": "0"
        },
        {
            "puesto": 5,
            "nombre": "Ernzer Marcel",
            "pais": "Luxemburgo",
            "equipo": "",
            "ventaja": "0"
        },
        {
            "puesto": 6,
            "nombre": "Storms Jan",
            "pais": "Bélgica",
            "equipo": "",
            "ventaja": "0"
        },
        {
            "puesto": 7,
            "nombre": "Impanis Raymond",
            "pais": "Bélgica",
            "equipo": "",
            "ventaja": "0"
        },
        {
            "puesto": 8,
            "nombre": "Decock Roger",
            "pais": "Bélgica",
            "equipo": "Bertin - D'Alessandro",
            "ventaja": "0"
        },
        {
            "puesto": 9,
            "nombre": "Peeters Ward",
            "pais": "Bélgica",
            "equipo": "",
            "ventaja": "0"
        },
        {
            "puesto": 10,
            "nombre": "Rosseel André",
            "pais": "Bélgica",
            "equipo": "",
            "ventaja": "0"
        }
    ],
    "ganadorPuntos": {},
    "ganadorMontana": {},
    "ganadorJovenes": {},
    "ganadorEquipos": {},
    "etapas": []
}