{
    "idCarrera": "bretagne-classic",
    "anio": 1960,
    "distancia": 200.0,
    "desnivel": 0,
    "tiempo": "5h 10' 00\"",
    "ciclistasInscritos": 3,
    "ciclistasFinalizados": 32,
    "clasificacionGeneral": [
        {
            "puesto": 1,
            "nombre": "Ferrer Hubert",
            "pais": "Francia",
            "equipo": "",
            "ventaja": "0"
        },
        {
            "puesto": 2,
            "nombre": "Foucher André",
            "pais": "Francia",
            "equipo": "",
            "ventaja": "+ 10 s"
        },
        {
            "puesto": 3,
            "nombre": "Velly Joseph",
            "pais": "Francia",
            "equipo": "",
            "ventaja": "+ 2 min 10 s"
        },
        {
            "puesto": 4,
            "nombre": "Le Buhotel Félix",
            "pais": "Francia",
            "equipo": "Mercier - BP - Hutchinson",
            "ventaja": "+ 2 min 10 s"
        },
        {
            "puesto": 5,
            "nombre": "Gainche Jean",
            "pais": "Francia",
            "equipo": "Mercier - BP - Hutchinson",
            "ventaja": "+ 2 min 10 s"
        },
        {
            "puesto": 6,
            "nombre": "Le Bigault Émile",
            "pais": "Francia",
            "equipo": "Mercier - BP - Hutchinson",
            "ventaja": "+ 2 min 10 s"
        },
        {
            "puesto": 7,
            "nombre": "Carfantan Marcel",
            "pais": "Francia",
            "equipo": "Rochet - Margnat",
            "ventaja": "+ 2 min 10 s"
        },
        {
            "puesto": 8,
            "nombre": "Thomin Joseph",
            "pais": "Francia",
            "equipo": "Liberia - Grammont",
            "ventaja": "+ 2 min 10 s"
        },
        {
            "puesto": 9,
            "nombre": "Audaire Armand",
            "pais": "Francia",
            "equipo": "",
            "ventaja": "+ 2 min 10 s"
        },
        {
            "puesto": 10,
            "nombre": "Amenda Richard",
            "pais": "Francia",
            "equipo": "",
            "ventaja": "+ 2 min 10 s"
        }
    ],
    "ganadorPuntos": {},
    "ganadorMontana": {},
    "ganadorJovenes": {},
    "ganadorEquipos": {},
    "etapas": []
}