{
    "idCarrera": "milano-sanremo",
    "anio": 1937,
    "distancia": 281.5,
    "desnivel": 0,
    "tiempo": "7h 31' 30\"",
    "ciclistasInscritos": 68,
    "ciclistasFinalizados": 68,
    "clasificacionGeneral": [
        {
            "puesto": 1,
            "nombre": "Del Cancia Cesare",
            "pais": "Italia",
            "equipo": "",
            "ventaja": "0"
        },
        {
            "puesto": 2,
            "nombre": "Favalli Pierino",
            "pais": "Italia",
            "equipo": "",
            "ventaja": "+ 2 min 20 s"
        },
        {
            "puesto": 3,
            "nombre": "Cimatti Marco",
            "pais": "Italia",
            "equipo": "",
            "ventaja": "+ 2 min 50 s"
        },
        {
            "puesto": 4,
            "nombre": "Masarati Attilio",
            "pais": "Italia",
            "equipo": "",
            "ventaja": "+ 2 min 50 s"
        },
        {
            "puesto": 5,
            "nombre": "Bizzi Olimpio",
            "pais": "Italia",
            "equipo": "",
            "ventaja": "+ 2 min 50 s"
        },
        {
            "puesto": 6,
            "nombre": "Bailo Osvaldo",
            "pais": "Italia",
            "equipo": "",
            "ventaja": "+ 2 min 50 s"
        },
        {
            "puesto": 6,
            "nombre": "Cazzulani Giovanni",
            "pais": "Italia",
            "equipo": "",
            "ventaja": "+ 2 min 50 s"
        },
        {
            "puesto": 6,
            "nombre": "Macchi Luigi",
            "pais": "Italia",
            "equipo": "",
            "ventaja": "+ 2 min 50 s"
        },
        {
            "puesto": 9,
            "nombre": "Bavutti Elio",
            "pais": "Italia",
            "equipo": "",
            "ventaja": "+ 2 min 50 s"
        },
        {
            "puesto": 9,
            "nombre": "Cinelli Giotto",
            "pais": "Italia",
            "equipo": "",
            "ventaja": "+ 2 min 50 s"
        }
    ],
    "ganadorPuntos": {},
    "ganadorMontana": {},
    "ganadorJovenes": {},
    "ganadorEquipos": {},
    "etapas": []
}