{
  "idCarrera": "europeo-ruta-2021",
  "anio": 2021,
  "distancia": 179.2,
  "desnivel": 3435,
  "tiempo": "4h 19' 45\"",
  "ciclistasInscritos": 0,
  "ciclistasFinalizados": 0,
  "clasificacionGeneral": [
    {
      "puesto": 1,
      "nombre": "Colbrelli Sonny",
      "pais": "Italia",
      "equipo": "Italia",
      "ventaja": "0"
    },
    {
      "puesto": 2,
      "nombre": "Evenepoel Remco",
      "pais": "Bélgica",
      "equipo": "Bélgica",
      "ventaja": "0"
    },
    {
      "puesto": 3,
      "nombre": "Cosnefroy Benoît",
      "pais": "Francia",
      "equipo": "Francia",
      "ventaja": "+ 1 min 30 s"
    },
    {
      "puesto": 4,
      "nombre": "Trentin Matteo",
      "pais": "Italia",
      "equipo": "Italia",
      "ventaja": "+ 1 min 44 s"
    },
    {
      "puesto": 5,
      "nombre": "Pogačar Tadej",
      "pais": "Eslovenia",
      "equipo": "Eslovenia",
      "ventaja": "+ 1 min 44 s"
    },
    {
      "puesto": 6,
      "nombre": "Hirschi Marc",
      "pais": "Suiza",
      "equipo": "Suiza",
      "ventaja": "+ 1 min 44 s"
    },
    {
      "puesto": 7,
      "nombre": "Hoelgaard Markus",
      "pais": "Noruega",
      "equipo": "Noruega",
      "ventaja": "+ 1 min 44 s"
    },
    {
      "puesto": 8,
      "nombre": "Hermans Ben",
      "pais": "Bélgica",
      "equipo": "Bélgica",
      "ventaja": "+ 1 min 46 s"
    },
    {
      "puesto": 9,
      "nombre": "Sivakov Pavel",
      "pais": "Rusia",
      "equipo": "Rusia",
      "ventaja": "+ 1 min 49 s"
    },
    {
      "puesto": 10,
      "nombre": "Campenaerts Victor",
      "pais": "Bélgica",
      "equipo": "Bélgica",
      "ventaja": "+ 5 min 41 s"
    }
  ],
  "ganadorPuntos": {},
  "ganadorMontana": {},
  "ganadorJovenes": {},
  "ganadorEquipos": {},
  "etapas": []
}