{
  "idCarrera": "olimpiadas-rr-1996",
  "anio": 1996,
  "distancia": 221.85,
  "desnivel": 2418,
  "tiempo": "4h 53' 56\"",
  "ciclistasInscritos": 0,
  "ciclistasFinalizados": 0,
  "clasificacionGeneral": [
    {
      "puesto": 1,
      "nombre": "Richard Pascal",
      "pais": "Suiza",
      "equipo": "Suiza",
      "ventaja": "0"
    },
    {
      "puesto": 2,
      "nombre": "Sørensen Rolf",
      "pais": "Dinamarca",
      "equipo": "Dinamarca",
      "ventaja": "0"
    },
    {
      "puesto": 3,
      "nombre": "Sciandri Maximilian",
      "pais": "Gran Bretaña",
      "equipo": "Gran Bretaña",
      "ventaja": "+ 2 s"
    },
    {
      "puesto": 4,
      "nombre": "Andreu Frankie",
      "pais": "Estados Unidos",
      "equipo": "Estados Unidos",
      "ventaja": "+ 1 min 14 s"
    },
    {
      "puesto": 5,
      "nombre": "Virenque Richard",
      "pais": "Francia",
      "equipo": "Francia",
      "ventaja": "+ 1 min 14 s"
    },
    {
      "puesto": 6,
      "nombre": "Mauri Melchor",
      "pais": "España",
      "equipo": "España",
      "ventaja": "+ 1 min 15 s"
    },
    {
      "puesto": 7,
      "nombre": "Baldato Fabio",
      "pais": "Italia",
      "equipo": "Italia",
      "ventaja": "+ 1 min 28 s"
    },
    {
      "puesto": 8,
      "nombre": "Bartoli Michele",
      "pais": "Italia",
      "equipo": "Italia",
      "ventaja": "+ 1 min 28 s"
    },
    {
      "puesto": 9,
      "nombre": "Spruch Zbigniew",
      "pais": "Polonia",
      "equipo": "Polonia",
      "ventaja": "+ 1 min 29 s"
    },
    {
      "puesto": 10,
      "nombre": "Museeuw Johan",
      "pais": "Bélgica",
      "equipo": "Bélgica",
      "ventaja": "+ 1 min 29 s"
    }
  ],
  "ganadorPuntos": {},
  "ganadorMontana": {},
  "ganadorJovenes": {},
  "ganadorEquipos": {},
  "etapas": []
}