{
    "idCarrera": "gent-wevelgem",
    "anio": 2014,
    "distancia": 233.0,
    "desnivel": 1502,
    "tiempo": "5h 34' 37\"",
    "ciclistasInscritos": 199,
    "ciclistasFinalizados": 199,
    "clasificacionGeneral": [
        {
            "puesto": 1,
            "nombre": "Degenkolb John",
            "pais": "Alemania",
            "equipo": "Team Giant - Shimano",
            "ventaja": "0"
        },
        {
            "puesto": 2,
            "nombre": "Démare Arnaud",
            "pais": "Francia",
            "equipo": "FDJ.fr ",
            "ventaja": "0"
        },
        {
            "puesto": 3,
            "nombre": "Sagan Peter",
            "pais": "Eslovaquia",
            "equipo": "Cannondale ",
            "ventaja": "0"
        },
        {
            "puesto": 4,
            "nombre": "Vanmarcke Sep",
            "pais": "Bélgica",
            "equipo": "Belkin-Pro Cycling Team",
            "ventaja": "0"
        },
        {
            "puesto": 5,
            "nombre": "Boonen Tom",
            "pais": "Bélgica",
            "equipo": "Omega Pharma - Quick-Step",
            "ventaja": "0"
        },
        {
            "puesto": 6,
            "nombre": "Van Asbroeck Tom",
            "pais": "Bélgica",
            "equipo": "Topsport Vlaanderen - Baloise",
            "ventaja": "0"
        },
        {
            "puesto": 7,
            "nombre": "Tsatevich Alexey",
            "pais": "Rusia",
            "equipo": "Team Katusha ",
            "ventaja": "0"
        },
        {
            "puesto": 8,
            "nombre": "Hutarovich Yauheni",
            "pais": "Bielorrusia",
            "equipo": "AG2R La Mondiale",
            "ventaja": "0"
        },
        {
            "puesto": 9,
            "nombre": "Hushovd Thor",
            "pais": "Noruega",
            "equipo": "BMC Racing Team",
            "ventaja": "0"
        },
        {
            "puesto": 10,
            "nombre": "Roelandts Jürgen",
            "pais": "Bélgica",
            "equipo": "Lotto Belisol ",
            "ventaja": "0"
        }
    ],
    "ganadorPuntos": {},
    "ganadorMontana": {},
    "ganadorJovenes": {},
    "ganadorEquipos": {},
    "etapas": []
}